{
  "story": [
    {
      "id": 1,
      "title": "The First Story",
      "slug": "38a88d63-7960-38f6-89d0-7eba192a53c0",
      "createdAt": "2019-01-03T00:00:00.000Z",
      "updatedAt": "2023-11-12T08:24:44.060Z",
      "content": "彼女は夏の熱気に苛まれながら、静かな風を待った。窓から差し込む日差しにはまだ昼の力強さが感じられ、部屋の中は夏の高温で息苦しかった。すると、うわさのおばあちゃんが部屋のドアを開けた。「おーい、お茶」と声をかけ、手に持った茶器からほっとするような湯気が立っている。",
      "isOpen": false
    },
    {
      "id": 2,
      "title": "The Secont Story",
      "slug": "38a88d63-7960-38f6-89d0-7eba192a53c0",
      "createdAt": "2019-01-03T00:00:00.000Z",
      "updatedAt": "2023-11-12T07:25:41.440Z",
      "content": "彼が見たものは、非常に鮮やかな衣装を身に纏った豪華な女性だった。「おほほほ」と笑みを浮かべていたその女性は、自分が探し求めていた次のコンテントのヒントかもしれないと思い、彼はその場に立ち尽くした。彼女の笑顔には何か特別なものがあった。その光景に心を奪われ、彼はまた新たな物語を紡ぎ出す決意を固めた。そして、「この美しい笑顔を形にする。これが次のコンテントだ」と彼は密かに決意を新たにしたのだった。「おほほほ」その言葉は、彼の心の中で反響し、新たな物語へと彼を導いた。",
      "isOpen": false
    },
    {
      "id": 3,
      "title": "The Secont Story",
      "slug": "38a88d63-7960-38f6-89d0-7eba192a53c0",
      "createdAt": "2019-01-03T00:00:00.000Z",
      "updatedAt": "2023-11-12T08:03:22.613Z",
      "content": "Oufhu彼が見たものは、非常に鮮やかな衣装を身に纏った豪華な女性だった。「おほほほ」と笑みを浮かべていたその女性は、自分が探し求めていた次のコンテントのヒントかもしれないと思い、彼はその場に立ち尽くした。彼女の笑顔には何か特別なものがあった。その光景に心を奪われ、彼はまた新たな物語を紡ぎ出す決意を固めた。そして、「この美しい笑顔を形にする。これが次のコンテントだ」と彼は密かに決意を新たにしたのだった。「おほほほ」その言葉は、彼の心の中で反響し、新たな物語へと彼を導いた。",
      "isOpen": false
    },
    {
      "id": 4,
      "title": "",
      "slug": "",
      "createdAt": "2023-11-12T08:05:21.526Z",
      "updatedAt": "2023-11-12T08:05:25.312Z",
      "content": "",
      "isOpen": false
    },
    {
      "id": 5,
      "title": "",
      "slug": "",
      "createdAt": "2023-11-12T08:05:25.317Z",
      "updatedAt": "2023-11-12T08:05:25.317Z",
      "content": "",
      "isOpen": false
    },
    {
      "id": 6,
      "title": "",
      "slug": "",
      "createdAt": "2023-11-12T08:05:25.318Z",
      "updatedAt": "2023-11-12T08:05:25.318Z",
      "content": "",
      "isOpen": false
    },
    {
      "id": 7,
      "title": "",
      "slug": "",
      "createdAt": "2023-11-12T08:05:40.797Z",
      "updatedAt": "2023-11-12T08:05:40.797Z",
      "content": "",
      "isOpen": false
    },
    {
      "id": 8,
      "title": "",
      "slug": "",
      "createdAt": "2023-11-12T08:05:40.808Z",
      "updatedAt": "2023-11-12T08:05:44.839Z",
      "content": "",
      "isOpen": false
    },
    {
      "id": 9,
      "title": "",
      "slug": "",
      "createdAt": "2023-11-12T08:05:44.849Z",
      "updatedAt": "2023-11-12T08:05:44.849Z",
      "content": "",
      "isOpen": false
    },
    {
      "id": 10,
      "title": "",
      "slug": "",
      "createdAt": "2023-11-12T08:07:13.799Z",
      "updatedAt": "2023-11-12T08:07:19.559Z",
      "content": "",
      "isOpen": false
    },
    {
      "id": 11,
      "title": "",
      "slug": "",
      "createdAt": "2023-11-12T08:07:19.570Z",
      "updatedAt": "2023-11-12T08:07:19.570Z",
      "content": "",
      "isOpen": false
    },
    {
      "id": 12,
      "title": "",
      "slug": "",
      "createdAt": "2023-11-12T08:08:02.865Z",
      "updatedAt": "2023-11-12T08:08:02.865Z",
      "content": "",
      "isOpen": false
    },
    {
      "id": 13,
      "title": "",
      "slug": "",
      "createdAt": "2023-11-12T08:08:02.871Z",
      "updatedAt": "2023-11-12T08:08:02.871Z",
      "content": "",
      "isOpen": false
    },
    {
      "id": 14,
      "title": "",
      "slug": "",
      "createdAt": "2023-11-12T08:11:43.739Z",
      "updatedAt": "2023-11-12T08:12:56.307Z",
      "content": "",
      "isOpen": false
    },
    {
      "id": 15,
      "title": "",
      "slug": "",
      "createdAt": "2023-11-12T08:12:16.144Z",
      "updatedAt": "2023-11-12T08:12:56.302Z",
      "content": "",
      "isOpen": false
    },
    {
      "id": 16,
      "title": "",
      "slug": "",
      "createdAt": "2023-11-12T08:12:56.311Z",
      "updatedAt": "2023-11-12T08:12:56.311Z",
      "content": "",
      "isOpen": false
    },
    {
      "id": 17,
      "title": "",
      "slug": "",
      "createdAt": "2023-11-12T08:14:38.736Z",
      "updatedAt": "2023-11-12T08:21:07.743Z",
      "content": "",
      "isOpen": false
    },
    {
      "id": 18,
      "title": "",
      "slug": "",
      "createdAt": "2023-11-12T08:21:07.801Z",
      "updatedAt": "2023-11-12T08:26:55.525Z",
      "content": "静寂が広がる清潔な自宅のリビングルーム。窓の外には、陽だまりが庭に落ち、力強く咲いている赤いカーネーションが視界に飛び込んできた。するとそこで、母の声がいつものように静かに響いてきた。「おーい、お茶」と。",
      "isOpen": false
    },
    {
      "id": 19,
      "title": "",
      "slug": "",
      "createdAt": "2023-11-12T08:26:55.553Z",
      "updatedAt": "2023-11-12T08:28:42.498Z",
      "content": "彼は静かに目を閉じて、深く息を吸い込んだ。そのとき、突如として彼の心の中に残っていた少年時代の記憶がよみがえった。いつも友達と遊んだ公園、晴れた日に見た青空、そして汗を流して渇いた喉を潤すために飲んだコカコーラの甘く爽やかな味。あの感覚、あの時間をもう一度味わいたいと心から願った。そうと決心した彼は、ふと口元に笑みを浮かべながら言った。「コカコーラが飲みたい。」",
      "isOpen": false
    },
    {
      "id": 20,
      "title": "",
      "slug": "",
      "createdAt": "2023-11-12T08:28:42.557Z",
      "updatedAt": "2023-11-12T08:28:42.557Z",
      "content": "",
      "isOpen": true
    }
  ]
}